package_nso_to_oc/README.md
package_nso_to_oc/__init__.py
package_nso_to_oc/common.py
package_nso_to_oc/main.py
package_nso_to_oc/xe/__init__.py
package_nso_to_oc/xe/common_xe.py
package_nso_to_oc/xe/main_xe.py
package_nso_to_oc/xe/xe_acls.py
package_nso_to_oc/xe/xe_bgp.py
package_nso_to_oc/xe/xe_interfaces.py
package_nso_to_oc/xe/xe_mpls.py
package_nso_to_oc/xe/xe_network_instances.py
package_nso_to_oc/xe/xe_ospfv2.py
package_nso_to_oc/xe/xe_routing_policy.py
package_nso_to_oc/xe/xe_static_route.py
package_nso_to_oc/xe/xe_stp.py
package_nso_to_oc/xe/xe_system.py
package_nso_to_oc/xe/xe_vlans.py
package_nso_to_oc/xr/__init__.py
package_nso_to_oc/xr/common_xr.py
package_nso_to_oc/xr/main_xr.py
package_nso_to_oc/xr/xr_acls.py
package_nso_to_oc/xr/xr_interfaces.py
package_nso_to_oc/xr/xr_mpls.py
package_nso_to_oc/xr/xr_network_instances.py
package_nso_to_oc/xr/xr_static_route.py
package_nso_to_oc/xr/xr_system.py
nso_oc-2.82.1.dist-info/LICENSE
nso_oc-2.82.1.dist-info/METADATA
nso_oc-2.82.1.dist-info/WHEEL
nso_oc-2.82.1.dist-info/entry_points.txt
nso_oc-2.82.1.dist-info/top_level.txt
nso_oc-2.82.1.dist-info/RECORD
