Metadata-Version: 2.1
Name: nso-oc
Version: 2.82.1
Summary: Cisco NSO OpenConfig Tools
License: CISCO SAMPLE CODE LICENSE
Project-URL: homepage, https://github.com/model-driven-devops/nso-oc-services
Classifier: License :: Other/Proprietary License
Classifier: Operating System :: POSIX :: Linux
Classifier: Programming Language :: Python :: 3
License-File: LICENSE
Requires-Dist: urllib3
